entityshape/__init__.py
entityshape/enums.py
entityshape/exceptions.py
entityshape/models/__init__.py
entityshape/models/compareshape.py
entityshape/models/property_value.py
entityshape/models/result.py
entityshape/models/result_property.py
entityshape/models/shape.py
entityshape/models/statement_value.py
entityshape-0.1.1.dist-info/LICENSE
entityshape-0.1.1.dist-info/METADATA
entityshape-0.1.1.dist-info/WHEEL
entityshape-0.1.1.dist-info/RECORD
