Metadata-Version: 2.1
Name: entityshape
Version: 0.1.1
Summary: Python library to validate Wikidata items.
Home-page: https://github.com/dpriskorn/entityshape
License: GPLv3+
Keywords: wikidata,entityschema,entity validation
Author: Mark Tully aka Teester
Requires-Python: >=3.8,<=3.12
Classifier: License :: Other/Proprietary License
Classifier: Programming Language :: Python :: 3
Classifier: Programming Language :: Python :: 3.8
Classifier: Programming Language :: Python :: 3.9
Classifier: Programming Language :: Python :: 3.10
Classifier: Programming Language :: Python :: 3.11
Classifier: Topic :: Software Development :: Libraries :: Python Modules
Requires-Dist: pydantic (>=1.10.9,<2.0.0)
Requires-Dist: requests (>=2.28.1,<3.0.0)
Requires-Dist: wikibaseintegrator (>=0.12.4,<0.13.0)
Project-URL: Repository, https://github.com/dpriskorn/entityshape
